SMPCbox/AbstractProtocol.py
SMPCbox/ProtocolParty.py
SMPCbox/SMPCSocket.py
SMPCbox/__init__.py
SMPCbox/dynamic_loading.py
SMPCbox/exceptions.py
SMPCbox/lobby.py
SMPCbox/lobby_gui.py
SMPCbox/main.py
implementedProtocols/MultClient2.py
implementedProtocols/MultiplicationProtocol.py
implementedProtocols/OT.py
implementedProtocols/Sum.py
implementedProtocols/TestProtocol.py
implementedProtocols/__init__.py
implementedProtocols/client2.py
SMPCbox-1.0.6.dist-info/LICENCE
SMPCbox-1.0.6.dist-info/METADATA
SMPCbox-1.0.6.dist-info/WHEEL
SMPCbox-1.0.6.dist-info/top_level.txt
SMPCbox-1.0.6.dist-info/RECORD
