Metadata-Version: 2.1
Name: SMPCbox
Version: 1.0.6
Summary: A framework for implementation of secure multi party computation protocols
Home-page: UNKNOWN
Author: Bas Jansweijer, Luuk Jonker, Zoltan Mann
Author-email: bas.jansweijer@student.uva.nl, luuk.jonker@student.uva.nl
License: UNKNOWN
Keywords: python,protocols,multi party computation,MPC,secure multi party computation,SMPC
Platform: UNKNOWN
License-File: LICENCE
